[
	{
		"id": 0,
		"sentTime": 1622711092274,
		"hashTime": 1622711092349,
		"txHash": "0xeac0f517e6a439ef1871d1e92b743a2f7c964243dda27fc56d59c13f3eb5dac8",
		"returnTime": 1622711092377,
		"blockNumber": 972,
		"txIndex": 0,
		"status": true,
		"gasUsed": 36250
	},
	{
		"id": 1,
		"sentTime": 1622711092274,
		"hashTime": 1622711092348,
		"txHash": "0xa393ef52165742360043678b8ebb297535f48436620b1be06ed5ab0a6c058eaa",
		"returnTime": 1622711092376,
		"blockNumber": 971,
		"txIndex": 1,
		"status": true,
		"gasUsed": 36250
	},
	{
		"id": 2,
		"sentTime": 1622711092274,
		"hashTime": 1622711092350,
		"txHash": "0x525e394ec89c9c6033fdeed7a3851499ab2f350604ad0548b25d52d63c995bcf",
		"returnTime": 1622711092379,
		"blockNumber": 972,
		"txIndex": 1,
		"status": true,
		"gasUsed": 36250
	},
	{
		"id": 3,
		"sentTime": 1622711092274,
		"hashTime": 1622711092353,
		"txHash": "0x4fe3a96988403710f98b22db678039524c4fe189d15ac954df4bfccc369c3fc6",
		"returnTime": 1622711092381,
		"blockNumber": 972,
		"txIndex": 2,
		"status": true,
		"gasUsed": 36250
	},
	{
		"id": 4,
		"sentTime": 1622711092274,
		"hashTime": 1622711092361,
		"txHash": "0xb8f43f63e1b38539a4aeb1e27556375cadab73a3d73a96ecf4c24c01af64c8b2",
		"returnTime": 1622711092390,
		"blockNumber": 972,
		"txIndex": 6,
		"status": true,
		"gasUsed": 36250
	},
	{
		"id": 5,
		"sentTime": 1622711092274,
		"hashTime": 1622711092358,
		"txHash": "0x13b8fc774cb3f2bd5072bb032c61f9f8f4ad918e6beb7466f49c153b97a74366",
		"returnTime": 1622711092387,
		"blockNumber": 972,
		"txIndex": 3,
		"status": true,
		"gasUsed": 36250
	},
	{
		"id": 6,
		"sentTime": 1622711092274,
		"hashTime": 1622711092363,
		"txHash": "0xe83f3d52f03401185c2f83d6d2b05732ed765f926644f5ebac534dd33a84e80c",
		"returnTime": 1622711092395,
		"blockNumber": 972,
		"txIndex": 7,
		"status": true,
		"gasUsed": 36250
	},
	{
		"id": 7,
		"sentTime": 1622711092274,
		"hashTime": 1622711092357,
		"txHash": "0x2b3abc77585e9aa449b17002e600d92e4bb0ec1484fc161d8bb8bc522600d602",
		"returnTime": 1622711092385,
		"blockNumber": 972,
		"txIndex": 5,
		"status": true,
		"gasUsed": 36250
	},
	{
		"id": 8,
		"sentTime": 1622711092274,
		"hashTime": 1622711092346,
		"txHash": "0xa5e51adfbc3de33e2554b99ddf453aab020956733f0131fb15b3841fff22bd78",
		"returnTime": 1622711092380,
		"blockNumber": 971,
		"txIndex": 0,
		"status": true,
		"gasUsed": 36250
	},
	{
		"id": 9,
		"sentTime": 1622711092274,
		"hashTime": 1622711092355,
		"txHash": "0xcc375a7ee3e070a8873ff1314ea6771c5302d394f88e98fa414163150e29deb2",
		"returnTime": 1622711092384,
		"blockNumber": 972,
		"txIndex": 4,
		"status": true,
		"gasUsed": 36250
	},
	{
		"x": "10",
		"totalTime": 121,
		"totalRate": 82.64462809917356
	}
]